bin2c.py
setup.py
bin2c.egg-info/PKG-INFO
bin2c.egg-info/SOURCES.txt
bin2c.egg-info/dependency_links.txt
bin2c.egg-info/entry_points.txt
bin2c.egg-info/top_level.txt